{
    "data": [
        {
            "id": "9",
            "username": "kit1",
            "email": "kit1@gmail.com",
            "password": "123456789",
            "device_number": "COSAI_VMS_456",
            "live_switch": "Non-Capture",
            "time": "2023-11-07 16:18:50",
            "phone": "712348207",
            "address": "MADURAI",
            "state": "kerala",
            "zipcode": "456123",
            "country": "India",
            "profile": "medium-shot-man-wearing-vr-glasses23.jpg",
            "kit_live_status": 0
        },
        {
            "id": "38",
            "username": "kit2",
            "email": "kit2@gmail.com",
            "password": "123456",
            "device_number": "COSAI_VMS_902",
            "live_switch": "Capture",
            "time": "2023-11-14 10:48:15",
            "phone": "345345",
            "address": "madurai",
            "state": "tamilnadu",
            "zipcode": "12345",
            "country": "India",
            "profile": "ipcamera24.png",
            "kit_live_status": 0
        },
        {
            "id": "39",
            "username": "kit3",
            "email": "kit3@gmail.com",
            "password": "asdfghjkl;",
            "device_number": "COSAI_VMS_542",
            "live_switch": "Non-Capture",
            "time": "2023-11-14 11:10:48",
            "phone": "1234567869",
            "address": "madurai",
            "state": "tamilnadu",
            "zipcode": "123456",
            "country": "India",
            "profile": "ipcamera1.png",
            "kit_live_status": 0
        }
    ]
}